toolri/__init__.py
toolri/version.py
toolri/toolri/__init__.py
toolri/toolri/main.py
toolri/toolri/controller/__init__.py
toolri/toolri/controller/controller.py
toolri/toolri/controller/image_manager.py
toolri/toolri/controller/settings.py
toolri/toolri/controller/tools/__init__.py
toolri/toolri/controller/tools/join_split.py
toolri/toolri/controller/tools/labeling.py
toolri/toolri/controller/tools/linking.py
toolri/toolri/controller/tools/manual.py
toolri/toolri/controller/tools/ocr.py
toolri/toolri/controller/tools/tool.py
toolri/toolri/model/__init__.py
toolri/toolri/model/data/__init__.py
toolri/toolri/model/data/data.py
toolri/toolri/model/geometry_functions/__init__.py
toolri/toolri/model/geometry_functions/geometry_functions.py
toolri/toolri/model/json/__init__.py
toolri/toolri/model/json/json_encoder.py
toolri/toolri/model/ocr/__init__.py
toolri/toolri/model/ocr/tesseract.py
toolri/toolri/view/__init__.py
toolri/toolri/view/view.py
toolri/toolri/view/panels/__init__.py
toolri/toolri/view/panels/data_manager.py
toolri/toolri/view/panels/image_canvas.py
toolri/toolri/view/panels/label_picker.py
toolri/toolri/view/panels/panel.py
toolri/toolri/view/panels/settings_manager.py
toolri/toolri/view/panels/tool_canvas.py
toolri/toolri/view/panels/tool_picker.py
toolri/toolri/view/panels/words_extractor.py
toolri/toolri/view/styles/__init__.py
toolri/toolri/view/styles/button.py
toolri/toolri/view/styles/canvas.py
toolri/toolri/view/styles/check_box.py
toolri/toolri/view/styles/color.py
toolri/toolri/view/styles/entry.py
toolri/toolri/view/styles/frame.py
toolri/toolri/view/styles/input_dialog.py
toolri/toolri/view/styles/label.py
toolri/toolri/view/styles/option_menu.py
toolri/toolri/view/styles/progress_bar.py
toolri/toolri/view/styles/radio_button.py
toolri/toolri/view/styles/scrollable_frame.py
toolri/toolri/view/styles/scrollbar.py
toolri/toolri/view/styles/segmented_button.py
toolri/toolri/view/styles/style_functions.py
toolri/toolri/view/styles/switch.py
toolri-1.0.4.dist-info/LICENSE
toolri-1.0.4.dist-info/METADATA
toolri-1.0.4.dist-info/WHEEL
toolri-1.0.4.dist-info/top_level.txt
toolri-1.0.4.dist-info/RECORD
